dockmate/__init__.py
dockmate/click.py
dockmate/config.py
dockmate/constants.py
dockmate/kernel.py
dockmate/assets/banner-logo.jpg
dockmate/assets/config.yaml
dockmate-0.1.14.dist-info/METADATA
dockmate-0.1.14.dist-info/WHEEL
dockmate-0.1.14.dist-info/entry_points.txt
dockmate-0.1.14.dist-info/licenses/LICENSE
dockmate-0.1.14.dist-info/RECORD
