Metadata-Version: 2.4
Name: dockmate
Version: 0.1.14
Summary: Monitors a list of specified Docker containers and automatically upgrades them when new images are released.
Project-URL: homepage, https://github.com/antrax2024/dockmate
Project-URL: Repository, https://github.com/antrax2024/dockmate
Author-email: Antrax <fredcox@gmail.com>
License: MIT
License-File: LICENSE
Requires-Python: >=3.13
Requires-Dist: click>=8.1.8
Requires-Dist: confz>=2.1.0
Requires-Dist: docker>=7.1.0
Requires-Dist: pushover-complete>=1.2.0
Requires-Dist: rich>=14.0.0
